common/logger/__init__.py
common/logger/log_wrapper.py
common/logger/logging.yml
common/polling/__init__.py
common/polling/condition_polling.py
common/utils/__init__.py
common/utils/httputil.py
common/utils/string_utils.py
logger/__init__.py
logger/log_wrapper.py
polling/__init__.py
polling/condition_polling.py
tests/__init__.py
tests/test_condition_polling.py
tests/test_string_utils.py
utils/__init__.py
utils/httputil.py
utils/string_utils.py
infra_common-1.1.0.2.dist-info/METADATA
infra_common-1.1.0.2.dist-info/WHEEL
infra_common-1.1.0.2.dist-info/top_level.txt
infra_common-1.1.0.2.dist-info/RECORD
