Metadata-Version: 2.1
Name: infra-common
Version: 1.1.0.2
Summary: common libraries for automation framework
Home-page: UNKNOWN
Author: Deep Instinct
Author-email: qa@deepinstinct.com
License: UNKNOWN
Platform: UNKNOWN
Classifier: Programming Language :: Python :: 3
Classifier: License :: OSI Approved :: MIT License
Classifier: Operating System :: OS Independent
Requires-Dist: pyYAML
